geocover_utils/__init__.py
geocover_utils/config.py
geocover_utils/downloader.py
geocover_utils/geometry.py
geocover_utils/logger.py
geocover_utils/raster.py
geocover_utils/stac_client.py
geocover_utils/swissalti.py
geocover_utils/utils.py
geocover_utils-0.4.0.dist-info/LICENSE.txt
geocover_utils-0.4.0.dist-info/METADATA
geocover_utils-0.4.0.dist-info/WHEEL
geocover_utils-0.4.0.dist-info/entry_points.txt
geocover_utils-0.4.0.dist-info/top_level.txt
geocover_utils-0.4.0.dist-info/RECORD
